<?xml version = '1.0' encoding = 'UTF-8'?>
<Table class="oracle.dbtools.crest.model.design.relational.Table" id="105A7511-D3F7-21E8-CB4C-96231109C833" directorySegmentName="seg_1" name="DPA_STATO_VERIFICA_CONS">
<sourceConnName>DOCSPA_MASTER</sourceConnName>
<sourceObjSchema>DOCSPA_MASTER</sourceObjSchema>
<sourceObjName>DPA_STATO_VERIFICA_CONS</sourceObjName>
<createdBy>mw</createdBy>
<createdTime>2014-06-06 11:31:01 UTC</createdTime>
<generatorID>Generato dall&apos;utente</generatorID>
<ownerDesignName>Schema_ER</ownerDesignName>
<schemaObject>DD90ABE9-F09C-01FB-CAC6-1C595D89499F</schemaObject>
<fonts itemClass="oracle.dbtools.crest.model.design.FontObjectWr">
<FontObject>
<foType>Titolo</foType>
<fontStyle>1</fontStyle>
<colorRGB>-16776961</colorRGB>
</FontObject>
<FontObject>
<foType>Colonna</foType>
<colorRGB>-16777216</colorRGB>
</FontObject>
<FontObject>
<foType>Tipo di dati</foType>
<colorRGB>-16744448</colorRGB>
</FontObject>
<FontObject>
<foType>Elemento chiave privata</foType>
<colorRGB>-16776961</colorRGB>
</FontObject>
<FontObject>
<foType>Elemento chiave esterna</foType>
<colorRGB>-16777216</colorRGB>
</FontObject>
<FontObject>
<foType>Elemento chiave univoca</foType>
<colorRGB>-16776961</colorRGB>
</FontObject>
<FontObject>
<foType>Non nullo</foType>
<colorRGB>-65536</colorRGB>
</FontObject>
<FontObject>
<foType>Chiave</foType>
<colorRGB>-16777216</colorRGB>
</FontObject>
</fonts>
<columns itemClass="oracle.dbtools.crest.model.design.relational.Column">
<Column name="SYSTEM_ID" id="F9272DE5-6BDE-15B0-E0B5-F4297E7E4AEA">
<sourceConnName>DOCSPA_MASTER</sourceConnName>
<sourceObjSchema>DPA_STATO_VERIFICA_CONS</sourceObjSchema>
<sourceObjName>SYSTEM_ID</sourceObjName>
<createdBy>mw</createdBy>
<createdTime>2014-06-06 11:31:22 UTC</createdTime>
<generatorID>Generato dall&apos;utente</generatorID>
<ownerDesignName>Schema_ER</ownerDesignName>
<nullsAllowed>true</nullsAllowed>
<useDomainConstraints>false</useDomainConstraints>
<use>1</use>
<logicalDatatype>LOGDT019</logicalDatatype>
<dataTypeSize>22</dataTypeSize>
<autoIncrementCycle>false</autoIncrementCycle>
</Column>
<Column name="VALORE" id="93B6349B-DECC-BA97-E2F3-18095C763E01">
<sourceConnName>DOCSPA_MASTER</sourceConnName>
<sourceObjSchema>DPA_STATO_VERIFICA_CONS</sourceObjSchema>
<sourceObjName>VALORE</sourceObjName>
<createdBy>mw</createdBy>
<createdTime>2014-06-06 11:31:22 UTC</createdTime>
<generatorID>Generato dall&apos;utente</generatorID>
<ownerDesignName>Schema_ER</ownerDesignName>
<nullsAllowed>true</nullsAllowed>
<useDomainConstraints>false</useDomainConstraints>
<use>1</use>
<logicalDatatype>LOGDT024</logicalDatatype>
<dataTypeSize>200 BYTE</dataTypeSize>
<autoIncrementCycle>false</autoIncrementCycle>
</Column>
</columns>
</Table>