<?xml version = '1.0' encoding = 'UTF-8'?>
<TableProxyOraclev11g class="oracle.dbtools.crest.model.design.storage.oracle.v11g.TableProxyOraclev11g" name="DPA_ASS_POLICY_PROFILAZIONE" id="4233DE02-7411-F79D-CA6B-5070B385C01B" directorySegmentName="seg_0">
<createdBy>mw</createdBy>
<createdTime>2014-06-06 11:30:59 UTC</createdTime>
<generatorID>Generato dall&apos;utente</generatorID>
<ownerDesignName>Schema_ER</ownerDesignName>
<logging>YES</logging>
<partitionedRowMovement>DISABLE</partitionedRowMovement>
<segment>01C269A7-E548-A726-A2EA-91C54D0C2BC0</segment>
<tableSpace>17BB0B62-C33B-CBD0-6CDC-922E0DE3574A</tableSpace>
<columnProxies>
<ColumnProxy class="oracle.dbtools.crest.model.design.storage.oracle.v11g.ColumnProxyOraclev11g" name="ID_OBJ_CUSTOM" id="1A7E9DCA-E103-3478-D6BD-B4FAA7E2D4FF">
<createdBy>mw</createdBy>
<createdTime>2014-06-06 11:31:06 UTC</createdTime>
<generatorID>Generato dall&apos;utente</generatorID>
<ownerDesignName>Schema_ER</ownerDesignName>
</ColumnProxy>
<ColumnProxy class="oracle.dbtools.crest.model.design.storage.oracle.v11g.ColumnProxyOraclev11g" name="ID_TEMPLATE" id="8FDE08DA-B29D-3910-14D4-26E1CCDDDF25">
<createdBy>mw</createdBy>
<createdTime>2014-06-06 11:31:06 UTC</createdTime>
<generatorID>Generato dall&apos;utente</generatorID>
<ownerDesignName>Schema_ER</ownerDesignName>
</ColumnProxy>
<ColumnProxy class="oracle.dbtools.crest.model.design.storage.oracle.v11g.ColumnProxyOraclev11g" name="ID_POLICY" id="9D6AF20D-B4C4-8D00-811D-993A90D06594">
<createdBy>mw</createdBy>
<createdTime>2014-06-06 11:31:06 UTC</createdTime>
<generatorID>Generato dall&apos;utente</generatorID>
<ownerDesignName>Schema_ER</ownerDesignName>
</ColumnProxy>
<ColumnProxy class="oracle.dbtools.crest.model.design.storage.oracle.v11g.ColumnProxyOraclev11g" name="VALORE" id="C7B00791-04B4-4981-7A5D-91A64A97F77B">
<createdBy>mw</createdBy>
<createdTime>2014-06-06 11:31:06 UTC</createdTime>
<generatorID>Generato dall&apos;utente</generatorID>
<ownerDesignName>Schema_ER</ownerDesignName>
</ColumnProxy>
</columnProxies>
<foreignKeys>
<ForeignKey class="oracle.dbtools.crest.model.design.storage.oracle.v10g.FKProxyOraclev10g" name="ASS_POLICY_PROFIL_POL_CONS_R01" id="4D041AEB-204D-8B48-2245-70E0DF2461CF">
<createdBy>mw</createdBy>
<createdTime>2014-06-06 11:32:09 UTC</createdTime>
<generatorID>Generato dall&apos;utente</generatorID>
<ownerDesignName>Schema_ER</ownerDesignName>
</ForeignKey>
<ForeignKey class="oracle.dbtools.crest.model.design.storage.oracle.v10g.FKProxyOraclev10g" name="ASS_POLICY_PROF_OGG_CUST_F_R05" id="60A5F4F1-D14C-4138-46D7-FADA3E040528">
<createdBy>mw</createdBy>
<createdTime>2014-06-06 11:32:09 UTC</createdTime>
<generatorID>Generato dall&apos;utente</generatorID>
<ownerDesignName>Schema_ER</ownerDesignName>
</ForeignKey>
<ForeignKey class="oracle.dbtools.crest.model.design.storage.oracle.v10g.FKProxyOraclev10g" name="ASS_POLICY_PROF_TIPO_ATTO_R02" id="85AD5EB3-9C50-1BCE-F87D-53A1CBD16B63">
<createdBy>mw</createdBy>
<createdTime>2014-06-06 11:32:09 UTC</createdTime>
<generatorID>Generato dall&apos;utente</generatorID>
<ownerDesignName>Schema_ER</ownerDesignName>
</ForeignKey>
<ForeignKey class="oracle.dbtools.crest.model.design.storage.oracle.v10g.FKProxyOraclev10g" name="ASS_POLICY_PROF_TIPO_FASC_R03" id="B01F1436-54AD-3360-7D9F-23855E6F5B6E">
<createdBy>mw</createdBy>
<createdTime>2014-06-06 11:32:09 UTC</createdTime>
<generatorID>Generato dall&apos;utente</generatorID>
<ownerDesignName>Schema_ER</ownerDesignName>
</ForeignKey>
<ForeignKey class="oracle.dbtools.crest.model.design.storage.oracle.v10g.FKProxyOraclev10g" name="ASS_POLICY_PROF_OGG_CUST_R04" id="F4ACC415-5C05-736D-8939-41984CF9C6F7">
<createdBy>mw</createdBy>
<createdTime>2014-06-06 11:32:09 UTC</createdTime>
<generatorID>Generato dall&apos;utente</generatorID>
<ownerDesignName>Schema_ER</ownerDesignName>
</ForeignKey>
</foreignKeys>
</TableProxyOraclev11g>