<?xml version = '1.0' encoding = 'UTF-8'?>
<Table class="oracle.dbtools.crest.model.design.relational.Table" id="433782AC-5CC6-56F1-2E18-D4B3FBC24228" directorySegmentName="seg_0" name="DPA_DISPOSITIVI_STAMPA">
<sourceConnName>DOCSPA_MASTER</sourceConnName>
<sourceObjSchema>DOCSPA_MASTER</sourceObjSchema>
<sourceObjName>DPA_DISPOSITIVI_STAMPA</sourceObjName>
<createdBy>mw</createdBy>
<createdTime>2014-06-06 11:31:00 UTC</createdTime>
<generatorID>Generato dall&apos;utente</generatorID>
<ownerDesignName>Schema_ER</ownerDesignName>
<schemaObject>DD90ABE9-F09C-01FB-CAC6-1C595D89499F</schemaObject>
<pkName>SYS_C00116155</pkName>
<fonts itemClass="oracle.dbtools.crest.model.design.FontObjectWr">
<FontObject>
<foType>Titolo</foType>
<fontStyle>1</fontStyle>
<colorRGB>-16776961</colorRGB>
</FontObject>
<FontObject>
<foType>Colonna</foType>
<colorRGB>-16777216</colorRGB>
</FontObject>
<FontObject>
<foType>Tipo di dati</foType>
<colorRGB>-16744448</colorRGB>
</FontObject>
<FontObject>
<foType>Elemento chiave privata</foType>
<colorRGB>-16776961</colorRGB>
</FontObject>
<FontObject>
<foType>Elemento chiave esterna</foType>
<colorRGB>-16777216</colorRGB>
</FontObject>
<FontObject>
<foType>Elemento chiave univoca</foType>
<colorRGB>-16776961</colorRGB>
</FontObject>
<FontObject>
<foType>Non nullo</foType>
<colorRGB>-65536</colorRGB>
</FontObject>
<FontObject>
<foType>Chiave</foType>
<colorRGB>-16777216</colorRGB>
</FontObject>
</fonts>
<columns itemClass="oracle.dbtools.crest.model.design.relational.Column">
<Column name="ID" id="C3331F8C-415F-4255-74F8-19851C1F72C2">
<sourceConnName>DOCSPA_MASTER</sourceConnName>
<sourceObjSchema>DPA_DISPOSITIVI_STAMPA</sourceObjSchema>
<sourceObjName>ID</sourceObjName>
<createdBy>mw</createdBy>
<createdTime>2014-06-06 11:31:11 UTC</createdTime>
<generatorID>Generato dall&apos;utente</generatorID>
<ownerDesignName>Schema_ER</ownerDesignName>
<useDomainConstraints>false</useDomainConstraints>
<use>1</use>
<logicalDatatype>LOGDT019</logicalDatatype>
<dataTypePrecision>1</dataTypePrecision>
<autoIncrementCycle>false</autoIncrementCycle>
</Column>
<Column name="CODE" id="8D974180-9E4C-74F9-9AD6-A5CD862019AA">
<sourceConnName>DOCSPA_MASTER</sourceConnName>
<sourceObjSchema>DPA_DISPOSITIVI_STAMPA</sourceObjSchema>
<sourceObjName>CODE</sourceObjName>
<createdBy>mw</createdBy>
<createdTime>2014-06-06 11:31:11 UTC</createdTime>
<generatorID>Generato dall&apos;utente</generatorID>
<ownerDesignName>Schema_ER</ownerDesignName>
<useDomainConstraints>false</useDomainConstraints>
<use>1</use>
<logicalDatatype>LOGDT024</logicalDatatype>
<dataTypeSize>50 BYTE</dataTypeSize>
<autoIncrementCycle>false</autoIncrementCycle>
</Column>
<Column name="DESCRIPTION" id="4284BB9D-03BA-0BC0-9AAA-15652E6978C8">
<sourceConnName>DOCSPA_MASTER</sourceConnName>
<sourceObjSchema>DPA_DISPOSITIVI_STAMPA</sourceObjSchema>
<sourceObjName>DESCRIPTION</sourceObjName>
<createdBy>mw</createdBy>
<createdTime>2014-06-06 11:31:11 UTC</createdTime>
<generatorID>Generato dall&apos;utente</generatorID>
<ownerDesignName>Schema_ER</ownerDesignName>
<useDomainConstraints>false</useDomainConstraints>
<use>1</use>
<logicalDatatype>LOGDT024</logicalDatatype>
<dataTypeSize>50 BYTE</dataTypeSize>
<autoIncrementCycle>false</autoIncrementCycle>
</Column>
</columns>
<indexes itemClass="oracle.dbtools.crest.model.design.relational.Index">
<ind_PK_UK id="626758BB-099E-8BAE-1A52-6608599D7EDE" name="SYS_C00116155">
<sourceConnName>DOCSPA_MASTER</sourceConnName>
<sourceObjSchema>DOCSPA_MASTER</sourceObjSchema>
<sourceObjName>SYS_C00116155</sourceObjName>
<createdBy>mw</createdBy>
<createdTime>2014-06-06 11:31:49 UTC</createdTime>
<generatorID>Generato dall&apos;utente</generatorID>
<ownerDesignName>Schema_ER</ownerDesignName>
<pk>true</pk>
<indexState>Primary Constraint</indexState>
<indexColumnUsage>
<colUsage columnID="C3331F8C-415F-4255-74F8-19851C1F72C2"/>
</indexColumnUsage>
</ind_PK_UK>
<ind_PK_UK id="EB0933A9-71F7-3FBE-D005-0CA460CFA52B" name="IX_SYS_C00116155">
<sourceConnName>DOCSPA_MASTER</sourceConnName>
<sourceObjSchema>DOCSPA_MASTER</sourceObjSchema>
<sourceObjName>SYS_C00116155</sourceObjName>
<createdBy>mw</createdBy>
<createdTime>2014-06-06 11:31:36 UTC</createdTime>
<generatorID>Generato dall&apos;utente</generatorID>
<ownerDesignName>Schema_ER</ownerDesignName>
<schemaObject>DD90ABE9-F09C-01FB-CAC6-1C595D89499F</schemaObject>
<indexState>Unique Plain Index</indexState>
<indexColumnUsage>
<colUsage columnID="C3331F8C-415F-4255-74F8-19851C1F72C2"/>
</indexColumnUsage>
</ind_PK_UK>
</indexes>
</Table>