<?xml version = '1.0' encoding = 'UTF-8'?>
<Table class="oracle.dbtools.crest.model.design.relational.Table" id="563953C6-A5E0-9E7D-35C2-44B67BB41D67" directorySegmentName="seg_0" name="DPA_ESITO_VERIFICA_CONS">
<sourceConnName>DOCSPA_MASTER</sourceConnName>
<sourceObjSchema>DOCSPA_MASTER</sourceObjSchema>
<sourceObjName>DPA_ESITO_VERIFICA_CONS</sourceObjName>
<createdBy>mw</createdBy>
<createdTime>2014-06-06 11:31:00 UTC</createdTime>
<generatorID>Generato dall&apos;utente</generatorID>
<ownerDesignName>Schema_ER</ownerDesignName>
<schemaObject>DD90ABE9-F09C-01FB-CAC6-1C595D89499F</schemaObject>
<pkName>DPA_ESITO_VERIFICA_CONS_PK</pkName>
<fonts itemClass="oracle.dbtools.crest.model.design.FontObjectWr">
<FontObject>
<foType>Titolo</foType>
<fontStyle>1</fontStyle>
<colorRGB>-16776961</colorRGB>
</FontObject>
<FontObject>
<foType>Colonna</foType>
<colorRGB>-16777216</colorRGB>
</FontObject>
<FontObject>
<foType>Tipo di dati</foType>
<colorRGB>-16744448</colorRGB>
</FontObject>
<FontObject>
<foType>Elemento chiave privata</foType>
<colorRGB>-16776961</colorRGB>
</FontObject>
<FontObject>
<foType>Elemento chiave esterna</foType>
<colorRGB>-16777216</colorRGB>
</FontObject>
<FontObject>
<foType>Elemento chiave univoca</foType>
<colorRGB>-16776961</colorRGB>
</FontObject>
<FontObject>
<foType>Non nullo</foType>
<colorRGB>-65536</colorRGB>
</FontObject>
<FontObject>
<foType>Chiave</foType>
<colorRGB>-16777216</colorRGB>
</FontObject>
</fonts>
<columns itemClass="oracle.dbtools.crest.model.design.relational.Column">
<Column name="SYSTEM_ID" id="89750D5E-2700-AAEE-34DF-96396F297C00">
<sourceConnName>DOCSPA_MASTER</sourceConnName>
<sourceObjSchema>DPA_ESITO_VERIFICA_CONS</sourceObjSchema>
<sourceObjName>SYSTEM_ID</sourceObjName>
<createdBy>mw</createdBy>
<createdTime>2014-06-06 11:31:12 UTC</createdTime>
<generatorID>Generato dall&apos;utente</generatorID>
<ownerDesignName>Schema_ER</ownerDesignName>
<useDomainConstraints>false</useDomainConstraints>
<use>1</use>
<logicalDatatype>LOGDT019</logicalDatatype>
<dataTypeSize>22</dataTypeSize>
<autoIncrementCycle>false</autoIncrementCycle>
</Column>
<Column name="VALORE" id="583C66BF-F401-7360-6286-C462E5FBD247">
<sourceConnName>DOCSPA_MASTER</sourceConnName>
<sourceObjSchema>DPA_ESITO_VERIFICA_CONS</sourceObjSchema>
<sourceObjName>VALORE</sourceObjName>
<createdBy>mw</createdBy>
<createdTime>2014-06-06 11:31:12 UTC</createdTime>
<generatorID>Generato dall&apos;utente</generatorID>
<ownerDesignName>Schema_ER</ownerDesignName>
<useDomainConstraints>false</useDomainConstraints>
<use>1</use>
<logicalDatatype>LOGDT024</logicalDatatype>
<dataTypeSize>200 BYTE</dataTypeSize>
<autoIncrementCycle>false</autoIncrementCycle>
</Column>
</columns>
<indexes itemClass="oracle.dbtools.crest.model.design.relational.Index">
<ind_PK_UK id="BF3E63B3-537C-7EFE-9C1F-0F9DBFE6DBD4" name="DPA_ESITO_VERIFICA_CONS_PK">
<sourceConnName>DOCSPA_MASTER</sourceConnName>
<sourceObjSchema>DOCSPA_MASTER</sourceObjSchema>
<sourceObjName>DPA_ESITO_VERIFICA_CONS_PK</sourceObjName>
<createdBy>mw</createdBy>
<createdTime>2014-06-06 11:31:36 UTC</createdTime>
<generatorID>Generato dall&apos;utente</generatorID>
<ownerDesignName>Schema_ER</ownerDesignName>
<schemaObject>DD90ABE9-F09C-01FB-CAC6-1C595D89499F</schemaObject>
<pk>true</pk>
<indexState>Primary Constraint</indexState>
<indexColumnUsage>
<colUsage columnID="89750D5E-2700-AAEE-34DF-96396F297C00"/>
</indexColumnUsage>
</ind_PK_UK>
</indexes>
</Table>