<?xml version = '1.0' encoding = 'UTF-8'?>
<TableProxyOraclev11g class="oracle.dbtools.crest.model.design.storage.oracle.v11g.TableProxyOraclev11g" name="DPA_OGGETTARIO" id="C1465E7B-F6B4-0012-800F-ECBE8F7419BA" directorySegmentName="seg_2">
<createdBy>mw</createdBy>
<createdTime>2014-06-06 11:31:00 UTC</createdTime>
<generatorID>Generato dall&apos;utente</generatorID>
<ownerDesignName>Schema_ER</ownerDesignName>
<logging>YES</logging>
<partitionedRowMovement>DISABLE</partitionedRowMovement>
<segment>80265F2A-B494-0793-9BE1-CA51470DE2D1</segment>
<tableSpace>17BB0B62-C33B-CBD0-6CDC-922E0DE3574A</tableSpace>
<columnProxies>
<ColumnProxy class="oracle.dbtools.crest.model.design.storage.oracle.v11g.ColumnProxyOraclev11g" name="ID_REGISTRO" id="22359CA9-6606-9A5F-0FF7-B5DAF9870E20">
<createdBy>mw</createdBy>
<createdTime>2014-06-06 11:31:18 UTC</createdTime>
<generatorID>Generato dall&apos;utente</generatorID>
<ownerDesignName>Schema_ER</ownerDesignName>
</ColumnProxy>
<ColumnProxy class="oracle.dbtools.crest.model.design.storage.oracle.v11g.ColumnProxyOraclev11g" name="ID_AMM" id="508232D1-6141-9843-8D03-7A719597CF39">
<createdBy>mw</createdBy>
<createdTime>2014-06-06 11:31:18 UTC</createdTime>
<generatorID>Generato dall&apos;utente</generatorID>
<ownerDesignName>Schema_ER</ownerDesignName>
</ColumnProxy>
<ColumnProxy class="oracle.dbtools.crest.model.design.storage.oracle.v11g.ColumnProxyOraclev11g" name="VAR_DESC_OGGETTO" id="D8406A7F-674C-A056-E5BD-218AE82DC7B7">
<createdBy>mw</createdBy>
<createdTime>2014-06-06 11:31:18 UTC</createdTime>
<generatorID>Generato dall&apos;utente</generatorID>
<ownerDesignName>Schema_ER</ownerDesignName>
</ColumnProxy>
<ColumnProxy class="oracle.dbtools.crest.model.design.storage.oracle.v11g.ColumnProxyOraclev11g" name="SYSTEM_ID" id="DBABCD2C-54BD-56A3-F7F0-CDDFD8359466">
<createdBy>mw</createdBy>
<createdTime>2014-06-06 11:31:18 UTC</createdTime>
<generatorID>Generato dall&apos;utente</generatorID>
<ownerDesignName>Schema_ER</ownerDesignName>
</ColumnProxy>
<ColumnProxy class="oracle.dbtools.crest.model.design.storage.oracle.v11g.ColumnProxyOraclev11g" name="CHA_OCCASIONALE" id="DC182B0E-7557-A1EE-F038-1ED7E484CF98">
<createdBy>mw</createdBy>
<createdTime>2014-06-06 11:31:18 UTC</createdTime>
<generatorID>Generato dall&apos;utente</generatorID>
<ownerDesignName>Schema_ER</ownerDesignName>
</ColumnProxy>
<ColumnProxy class="oracle.dbtools.crest.model.design.storage.oracle.v11g.ColumnProxyOraclev11g" name="VAR_COD_OGGETTO" id="FC06C386-C9C7-2001-A1A0-6D89504C5E69">
<createdBy>mw</createdBy>
<createdTime>2014-06-06 11:31:18 UTC</createdTime>
<generatorID>Generato dall&apos;utente</generatorID>
<ownerDesignName>Schema_ER</ownerDesignName>
</ColumnProxy>
</columnProxies>
<indexProxies>
<IndexProxy class="oracle.dbtools.crest.model.design.storage.oracle.v10g.IndexProxyOraclev10g" name="INDX_UPPER_VAR_DESC_OGGETTO" id="35D22F90-7D4D-7AF0-362F-522FA216296A">
<createdBy>mw</createdBy>
<createdTime>2014-06-06 11:31:38 UTC</createdTime>
<generatorID>Generato dall&apos;utente</generatorID>
<ownerDesignName>Schema_ER</ownerDesignName>
<segment>62CD8B99-8ED3-B3AB-B688-7A7517FBD673</segment>
<sortedRows>SORTED</sortedRows>
<tableSpace>59E1EAF8-88C9-CB2B-C77F-87733ACEBD22</tableSpace>
</IndexProxy>
<IndexProxy class="oracle.dbtools.crest.model.design.storage.oracle.v10g.IndexProxyOraclev10g" name="IX_SYS_C00116282" id="3C1B494B-2D44-477A-9D96-3E1FF4FCE24E">
<createdBy>mw</createdBy>
<createdTime>2014-06-06 11:31:38 UTC</createdTime>
<generatorID>Generato dall&apos;utente</generatorID>
<ownerDesignName>Schema_ER</ownerDesignName>
<segment>85C31F75-6057-A90D-AC49-747520F157B3</segment>
<sortedRows>SORTED</sortedRows>
<tableSpace>59E1EAF8-88C9-CB2B-C77F-87733ACEBD22</tableSpace>
</IndexProxy>
<IndexProxy class="oracle.dbtools.crest.model.design.storage.oracle.v10g.IndexProxyOraclev10g" name="IDX_DPA_OGGETTARIO" id="98E17957-197A-A097-D64D-5C58258F1699">
<createdBy>mw</createdBy>
<createdTime>2014-06-06 11:31:38 UTC</createdTime>
<generatorID>Generato dall&apos;utente</generatorID>
<ownerDesignName>Schema_ER</ownerDesignName>
<segment>155791D1-953D-99B0-533C-D3120B31818B</segment>
<sortedRows>SORTED</sortedRows>
<tableSpace>59E1EAF8-88C9-CB2B-C77F-87733ACEBD22</tableSpace>
</IndexProxy>
<IndexProxy class="oracle.dbtools.crest.model.design.storage.oracle.v10g.IndexProxyOraclev10g" name="INDX_OGG2" id="ABD0ED63-A9DE-9D0E-9E20-774E303614E8">
<createdBy>mw</createdBy>
<createdTime>2014-06-06 11:31:38 UTC</createdTime>
<generatorID>Generato dall&apos;utente</generatorID>
<ownerDesignName>Schema_ER</ownerDesignName>
<segment>AB9AAE11-EEA8-5638-931E-A8355B3469A3</segment>
<sortedRows>SORTED</sortedRows>
<tableSpace>59E1EAF8-88C9-CB2B-C77F-87733ACEBD22</tableSpace>
</IndexProxy>
</indexProxies>
<foreignKeys>
<ForeignKey class="oracle.dbtools.crest.model.design.storage.oracle.v10g.FKProxyOraclev10g" name="DPA_OGGETTARIO_R01" id="B34289EA-4C13-157B-18B5-3D4AC81B2DAF">
<createdBy>mw</createdBy>
<createdTime>2014-06-06 11:32:09 UTC</createdTime>
<generatorID>Generato dall&apos;utente</generatorID>
<ownerDesignName>Schema_ER</ownerDesignName>
</ForeignKey>
<ForeignKey class="oracle.dbtools.crest.model.design.storage.oracle.v10g.FKProxyOraclev10g" name="DPA_OGGETTARIO_R02" id="DA41F279-7D36-4F84-0DAB-70C353F7591B">
<createdBy>mw</createdBy>
<createdTime>2014-06-06 11:32:09 UTC</createdTime>
<generatorID>Generato dall&apos;utente</generatorID>
<ownerDesignName>Schema_ER</ownerDesignName>
</ForeignKey>
</foreignKeys>
<primaryKeys>
<PrimaryKey class="oracle.dbtools.crest.model.design.storage.oracle.v10g.PKProxyOraclev10g" name="SYS_C00116282" id="7C60A5DF-1BEF-2BB8-4BD2-7F8A02699C9A">
<createdBy>mw</createdBy>
<createdTime>2014-06-06 11:31:54 UTC</createdTime>
<generatorID>Generato dall&apos;utente</generatorID>
<ownerDesignName>Schema_ER</ownerDesignName>
<sortedRows>SORTED</sortedRows>
<tableSpace>17BB0B62-C33B-CBD0-6CDC-922E0DE3574A</tableSpace>
<existingIndex>3C1B494B-2D44-477A-9D96-3E1FF4FCE24E</existingIndex>
<indexSort>SORTED</indexSort>
<usingIndex>BY INDEX NAME</usingIndex>
</PrimaryKey>
</primaryKeys>
</TableProxyOraclev11g>