<?xml version = '1.0' encoding = 'UTF-8'?>
<FKIndexAssociation class="oracle.dbtools.crest.model.design.relational.FKIndexAssociation" id="3023B725-5DE0-9616-175F-9C3F71E7A886" directorySegmentName="seg_1" name="DPA_CORR_GLOBALI_R02">
<sourceConnName>DOCSPA_MASTER</sourceConnName>
<sourceObjSchema>DOCSPA_MASTER</sourceObjSchema>
<sourceObjName>DPA_CORR_GLOBALI_R02</sourceObjName>
<createdBy>mw</createdBy>
<createdTime>2014-06-06 11:32:09 UTC</createdTime>
<generatorID>Generato dall&apos;utente</generatorID>
<ownerDesignName>Schema_ER</ownerDesignName>
<containerWithKeyObject>0317F2DB-364C-1088-B6E0-C1AB95F1D212</containerWithKeyObject>
<deleteRule>NO ACTION</deleteRule>
<localFKIndex>C5A6EAE5-2308-2412-AB6F-BD436303294F</localFKIndex>
<keyObject>58DFA322-4847-19AC-7723-56225C54D343</keyObject>
<mandatory>false</mandatory>
<transferable>true</transferable>
</FKIndexAssociation>